hebill_string/README.MD
hebill_string/__init__.py
hebill_string/constants.py
hebill_string/core.py
hebill_string-1.0.0.dist-info/METADATA
hebill_string-1.0.0.dist-info/WHEEL
hebill_string-1.0.0.dist-info/top_level.txt
hebill_string-1.0.0.dist-info/RECORD
