Metadata-Version: 2.1
Name: hebill_string
Version: 1.0.0
Summary: python字符串扩展类
Requires-Python: >=3.12
